builddriver/__init__.py
builddriver/__main__.py
builddriver/builddriver.py
builddriver-0.9.0.dist-info/METADATA
builddriver-0.9.0.dist-info/WHEEL
builddriver-0.9.0.dist-info/entry_points.txt
builddriver-0.9.0.dist-info/top_level.txt
builddriver-0.9.0.dist-info/RECORD
