Metadata-Version: 2.1
Name: builddriver
Version: 0.9.0
Summary: Execute make, cmake, maven and parses gcc/llvm output
Home-page: http://github.com/hgn/builddriver
Author: Hagen Paul Pfeifer
Author-email: hagen@jauu.net
License: MIT
Platform: UNKNOWN
Classifier: Development Status :: 4 - Beta
Classifier: Intended Audience :: Developers
Classifier: Topic :: Software Development :: Build Tools
Classifier: License :: OSI Approved :: MIT License
Classifier: Programming Language :: Python :: 3
Classifier: Programming Language :: Python :: 3.7
